[
  {
    "project": "B/S of 1000 Block of Bute St from Nelson St to Comox St\r\nE/S of 1000-1100 Block",
    "street": null,
    "location": "B/S of 1000 Block of Bute St from Nelson St to Comox St\r\nE/S of 1000-1100 Block",
    "comp_date": "2025-11-01",
    "url_link": "http://vanmapp1.vancouver.ca/roadahead/events/details/b592eeeb-a7fe-429c-88ca-9ad18cf6c5cd",
    "geom": {
      "type": "Feature",
      "geometry": {
        "coordinates": [
          [
            [
              -123.13021142265833,
              49.283898867434374
            ],
            [
              -123.1312359550511,
              49.28320075789196
            ]
          ],
          [
            [
              -123.13177239685399,
              49.28282807882684
            ],
            [
              -123.13204598217335,
              49.28264086339783
            ]
          ],
          [
            [
              -123.1322712877306,
              49.2824903906687
            ],
            [
              -123.13210230856266,
              49.28238191004428
            ]
          ]
        ],
        "type": "MultiLineString"
      },
      "properties": {}
    },
    "geo_point_2d": {
      "lon": -123.13111125706449,
      "lat": 49.28327108906166
    }
  },
  {
    "project": "Both Sides of 2500-2800 Block of Ash St from W Broadway to Lane South of W 12th",
    "street": null,
    "location": "Both Sides of 2500-2800 Block of Ash St from W Broadway to Lane South of W 12th",
    "comp_date": "2025-11-01",
    "url_link": "http://vanmapp1.vancouver.ca/roadahead/events/details/9ba145a1-75c7-403b-923a-6ef66edd5dbb",
    "geom": {
      "type": "Feature",
      "geometry": {
        "coordinates": [
          [
            [
              -123.11752238834478,
              49.26323114218363
            ],
            [
              -123.1176353667345,
              49.25996272219626
            ]
          ],
          [
            [
              -123.11926049637891,
              49.26044917710783
            ],
            [
              -123.11691951982024,
              49.26041634255705
            ]
          ]
        ],
        "type": "MultiLineString"
      },
      "properties": {}
    },
    "geo_point_2d": {
      "lon": -123.11779212632041,
      "lat": 49.26111122784101
    }
  },
  {
    "project": "Vine St from W 49th Av to Ln N of W 49th Av",
    "street": null,
    "location": "Vine St from W 49th Av to Ln N of W 49th Av",
    "comp_date": "2025-11-03",
    "url_link": "http://vanmapp1.vancouver.ca/roadahead/events/details/05ac357a-902f-43d0-a3e0-9a7048c15daf",
    "geom": {
      "type": "Feature",
      "geometry": {
        "coordinates": [
          [
            [
              -123.16018447680877,
              49.227853918367146
            ],
            [
              -123.16019234034184,
              49.227669243668885
            ]
          ],
          [
            [
              -123.16019234034184,
              49.227669243668885
            ],
            [
              -123.16021190874055,
              49.22722214284386
            ]
          ]
        ],
        "type": "MultiLineString"
      },
      "properties": {}
    },
    "geo_point_2d": {
      "lon": -123.16019811536374,
      "lat": 49.22753802726337
    }
  },
  {
    "project": "Fremlin St from W 49th Av to W 52nd Av",
    "street": null,
    "location": "Fremlin St from W 49th Av to W 52nd Av",
    "comp_date": "2025-11-03",
    "url_link": "http://vanmapp1.vancouver.ca/roadahead/events/details/5e7885dc-72f2-45f0-a35e-227296973a62",
    "geom": {
      "type": "Feature",
      "geometry": {
        "coordinates": [
          [
            [
              -123.12674419511228,
              49.22595901982223
            ],
            [
              -123.12681291665005,
              49.22389112131208
            ]
          ],
          [
            [
              -123.12672641786389,
              49.22649401474635
            ],
            [
              -123.12674419511228,
              49.22595901982223
            ]
          ]
        ],
        "type": "MultiLineString"
      },
      "properties": {}
    },
    "geo_point_2d": {
      "lon": -123.12676966646481,
      "lat": 49.225192568002896
    }
  },
  {
    "project": "W 37th Av from Cambie St to Alberta St",
    "street": null,
    "location": "W 37th Av from Cambie St to Alberta St",
    "comp_date": "2025-11-03",
    "url_link": "http://vanmapp1.vancouver.ca/roadahead/events/details/e1f12c74-3208-4b80-b349-8239415c4dad",
    "geom": {
      "type": "Feature",
      "geometry": {
        "coordinates": [
          [
            [
              -123.1151756940655,
              49.2371862122568
            ],
            [
              -123.11604550504451,
              49.237247840778025
            ]
          ],
          [
            [
              -123.11448135341534,
              49.23713138374589
            ],
            [
              -123.1151756940655,
              49.2371862122568
            ]
          ],
          [
            [
              -123.11327797127966,
              49.23703662668254
            ],
            [
              -123.11448135341534,
              49.23713138374589
            ]
          ]
        ],
        "type": "MultiLineString"
      },
      "properties": {}
    },
    "geo_point_2d": {
      "lon": -123.11466156391008,
      "lat": 49.23714456391849
    }
  },
  {
    "project": "B/S of 3900 Block of Crown St from W 23 Ave to Lane South\r\nB/S of 3700 Block of",
    "street": null,
    "location": "B/S of 3900 Block of Crown St from W 23 Ave to Lane South\r\nB/S of 3700 Block of",
    "comp_date": "2025-11-05",
    "url_link": "http://vanmapp1.vancouver.ca/roadahead/events/details/04fafb4e-fd6c-4456-a28a-bd1a32622aab",
    "geom": {
      "type": "Feature",
      "geometry": {
        "coordinates": [
          [
            [
              -123.19361851796235,
              49.251981345058994
            ],
            [
              -123.19361851796235,
              49.25154952215607
            ]
          ],
          [
            [
              -123.1936019259291,
              49.25378672947869
            ],
            [
              -123.19359675750833,
              49.25291973794339
            ]
          ],
          [
            [
              -123.1935807630935,
              49.255595019263694
            ],
            [
              -123.19358593151429,
              49.25472805948891
            ]
          ],
          [
            [
              -123.19357052817436,
              49.257466834300544
            ],
            [
              -123.19357052817439,
              49.25653581492671
            ]
          ],
          [
            [
              -123.19357970318977,
              49.258046735414354
            ],
            [
              -123.19396736661538,
              49.258048861547366
            ]
          ],
          [
            [
              -123.19606492612075,
              49.25808220263812
            ],
            [
              -123.19502154681398,
              49.258066447672576
            ]
          ],
          [
            [
              -123.19714516858222,
              49.258125132655096
            ],
            [
              -123.19628149727944,
              49.258114629354424
            ]
          ],
          [
            [
              -123.20060764671835,
              49.25815236777345
            ],
            [
              -123.19976543308768,
              49.258141864478574
            ]
          ]
        ],
        "type": "MultiLineString"
      },
      "properties": {}
    },
    "geo_point_2d": {
      "lon": -123.1952518090127,
      "lat": 49.25642988257106
    }
  },
  {
    "project": "1000 block of W 27th Ave between Osler St and Oak St",
    "street": null,
    "location": "1000 block of W 27th Ave between Osler St and Oak St",
    "comp_date": "2025-11-05",
    "url_link": "http://vanmapp1.vancouver.ca/roadahead/events/details/9bdf154a-c759-41db-a293-134d4567fe74",
    "geom": {
      "type": "Feature",
      "geometry": {
        "coordinates": [
          [
            [
              -123.12921880956934,
              49.247256075077075
            ],
            [
              -123.12990070361347,
              49.24726698619082
            ]
          ],
          [
            [
              -123.12833359537797,
              49.247241895819286
            ],
            [
              -123.12921880956934,
              49.247256075077075
            ]
          ],
          [
            [
              -123.12761886185562,
              49.247230445036735
            ],
            [
              -123.12833359537797,
              49.247241895819286
            ]
          ]
        ],
        "type": "MultiLineString"
      },
      "properties": {}
    },
    "geo_point_2d": {
      "lon": -123.1287597826582,
      "lat": 49.247248720381656
    }
  },
  {
    "project": "North Side of 1400 Block of E 33rd Ave from Knight St to 55m East of Knight St a",
    "street": null,
    "location": "North Side of 1400 Block of E 33rd Ave from Knight St to 55m East of Knight St a",
    "comp_date": "2025-11-06",
    "url_link": "http://vanmapp1.vancouver.ca/roadahead/events/details/25437800-0ef7-4e89-8fd4-b670c2289795",
    "geom": {
      "type": "Feature",
      "geometry": {
        "coordinates": [
          [
            [
              -123.0764021054828,
              49.24022801034644
            ],
            [
              -123.0752368412356,
              49.24021631025798
            ]
          ],
          [
            [
              -123.0736233981919,
              49.24018589052915
            ],
            [
              -123.07090922878025,
              49.24015079065393
            ]
          ]
        ],
        "type": "MultiLineString"
      },
      "properties": {}
    },
    "geo_point_2d": {
      "lon": -123.07333355018551,
      "lat": 49.24018450602525
    }
  },
  {
    "project": "Both Sides of 1000 Block of Bute St from Nelson St to Comox St",
    "street": null,
    "location": "Both Sides of 1000 Block of Bute St from Nelson St to Comox St",
    "comp_date": "2025-11-06",
    "url_link": "http://vanmapp1.vancouver.ca/roadahead/events/details/19a9fef1-4e7c-4153-8f30-2f747f443a96",
    "geom": {
      "type": "Feature",
      "geometry": {
        "coordinates": [
          [
            -123.13017645816552,
            49.28389479450291
          ],
          [
            -123.13123902049105,
            49.28319610166483
          ]
        ],
        "type": "LineString"
      },
      "properties": {}
    },
    "geo_point_2d": {
      "lon": -123.13070773932829,
      "lat": 49.28354544808387
    }
  },
  {
    "project": "Kersland Dr - W 35th Av to W 37th Av",
    "street": null,
    "location": "Kersland Dr - W 35th Av to W 37th Av",
    "comp_date": "2025-11-07",
    "url_link": "http://vanmapp1.vancouver.ca/roadahead/events/details/980b4a46-f9ca-4c7a-be32-c9c91bf33643",
    "geom": {
      "type": "Feature",
      "geometry": {
        "coordinates": [
          [
            -123.11544888345814,
            49.239701747919725
          ],
          [
            -123.11462251931519,
            49.23897398147048
          ],
          [
            -123.1144831328449,
            49.23856460807423
          ],
          [
            -123.11445326425043,
            49.23802526929299
          ],
          [
            -123.1144831328449,
            49.23712852496601
          ]
        ],
        "type": "LineString"
      },
      "properties": {}
    },
    "geo_point_2d": {
      "lon": -123.1146908507037,
      "lat": 49.238533677138136
    }
  },
  {
    "project": "North Side of 1400-1500 Block of Alberni St from Cardero St to 15m East of Nicol",
    "street": null,
    "location": "North Side of 1400-1500 Block of Alberni St from Cardero St to 15m East of Nicol",
    "comp_date": "2025-11-07",
    "url_link": "http://vanmapp1.vancouver.ca/roadahead/events/details/71891bcd-0881-469d-9c53-7ecb2eac5745",
    "geom": {
      "type": "Feature",
      "geometry": {
        "coordinates": [
          [
            [
              -123.12942470597284,
              49.289802592739676
            ],
            [
              -123.13004006187779,
              49.28939789054209
            ]
          ],
          [
            [
              -123.13122781742351,
              49.29015862534149
            ],
            [
              -123.13005810609384,
              49.289395992867384
            ]
          ],
          [
            [
              -123.13004955934764,
              49.28939861356619
            ],
            [
              -123.12991539743784,
              49.28931230779784
            ]
          ]
        ],
        "type": "MultiLineString"
      },
      "properties": {}
    },
    "geo_point_2d": {
      "lon": -123.13030444607118,
      "lat": 49.28969106444507
    }
  },
  {
    "project": "Both Sides of 1200 Block of Napier St from Vernon Dr to Clark Dr",
    "street": null,
    "location": "Both Sides of 1200 Block of Napier St from Vernon Dr to Clark Dr",
    "comp_date": "2025-11-07",
    "url_link": "http://vanmapp1.vancouver.ca/roadahead/events/details/d70508ab-e803-4f87-8d2e-4aab0ef451df",
    "geom": {
      "type": "Feature",
      "geometry": {
        "coordinates": [
          [
            -123.07864720728145,
            49.27496188802721
          ],
          [
            -123.0772902306941,
            49.274947821924684
          ]
        ],
        "type": "LineString"
      },
      "properties": {}
    },
    "geo_point_2d": {
      "lon": -123.07796871898779,
      "lat": 49.274954854975945
    }
  },
  {
    "project": "B/S of 1100 blk of Chilco St",
    "street": null,
    "location": "B/S of 1100 blk of Chilco St",
    "comp_date": "2025-11-08",
    "url_link": "http://vanmapp1.vancouver.ca/roadahead/events/details/6f821599-a1a0-44db-96e2-be0874285c3d",
    "geom": {
      "type": "Feature",
      "geometry": {
        "coordinates": [
          [
            -123.14370648224629,
            49.28987499265915
          ],
          [
            -123.14425625120018,
            49.289516414248965
          ]
        ],
        "type": "LineString"
      },
      "properties": {}
    },
    "geo_point_2d": {
      "lon": -123.14398136672325,
      "lat": 49.28969570345406
    }
  },
  {
    "project": "L/W Oak St - W 27th Av to W 9th Av",
    "street": null,
    "location": "L/W Oak St - W 27th Av to W 9th Av",
    "comp_date": "2025-11-13",
    "url_link": "http://vanmapp1.vancouver.ca/roadahead/events/details/5a98986a-1604-4845-9834-e9c8a6c9fe1c",
    "geom": {
      "type": "Feature",
      "geometry": {
        "coordinates": [
          [
            [
              -123.12834903400865,
              49.24724750328073
            ],
            [
              -123.12836472356973,
              49.246785760519515
            ]
          ],
          [
            [
              -123.12836472356973,
              49.246785760519515
            ],
            [
              -123.12838033682115,
              49.24632649149328
            ]
          ],
          [
            [
              -123.12838033682115,
              49.24632649149328
            ],
            [
              -123.12839570604346,
              49.24587389716393
            ]
          ],
          [
            [
              -123.12839570604346,
              49.24587389716393
            ],
            [
              -123.12841158636657,
              49.24540656803231
            ]
          ]
        ],
        "type": "MultiLineString"
      },
      "properties": {}
    },
    "geo_point_2d": {
      "lon": -123.12838031196637,
      "lat": 49.24632703571696
    }
  },
  {
    "project": "Both Sides of the Street of 8100-8200 Block of Ross St. From E Kent Av North to",
    "street": null,
    "location": "Both Sides of the Street of 8100-8200 Block of Ross St. From E Kent Av North to",
    "comp_date": "2025-11-13",
    "url_link": "http://vanmapp1.vancouver.ca/roadahead/events/details/6223fec8-513c-4f9b-a4ca-d1828f5fe727",
    "geom": {
      "type": "Feature",
      "geometry": {
        "coordinates": [
          [
            -123.08399375804058,
            49.20987900593815
          ],
          [
            -123.08419910011487,
            49.208783452301645
          ]
        ],
        "type": "LineString"
      },
      "properties": {}
    },
    "geo_point_2d": {
      "lon": -123.08409642907775,
      "lat": 49.2093312291199
    }
  },
  {
    "project": "Both Sides of the Street of 5700-5900 Block of Highbury St. From 85m South of W",
    "street": null,
    "location": "Both Sides of the Street of 5700-5900 Block of Highbury St. From 85m South of W",
    "comp_date": "2025-11-13",
    "url_link": "http://vanmapp1.vancouver.ca/roadahead/events/details/926cc261-cdcf-4e8e-8d8d-1ad43814d7bc",
    "geom": {
      "type": "Feature",
      "geometry": {
        "coordinates": [
          [
            -123.1884049870168,
            49.23396409730009
          ],
          [
            -123.18842654658359,
            49.233348190228725
          ]
        ],
        "type": "LineString"
      },
      "properties": {}
    },
    "geo_point_2d": {
      "lon": -123.18841576680019,
      "lat": 49.23365614376441
    }
  },
  {
    "project": "Fir St  Off-Ramp",
    "street": null,
    "location": "Fir St  Off-Ramp",
    "comp_date": "2025-11-18",
    "url_link": "http://vanmapp1.vancouver.ca/roadahead/events/details/ca55b5ab-70e3-4c32-b39c-47b09e49c257",
    "geom": {
      "type": "Feature",
      "geometry": {
        "coordinates": [
          [
            -123.13947926712845,
            49.26853242075305
          ],
          [
            -123.13961406802444,
            49.2684474601983
          ],
          [
            -123.13968424522147,
            49.26840019555567
          ],
          [
            -123.13973781357743,
            49.26836625485896
          ],
          [
            -123.13977769191911,
            49.268332672516976
          ],
          [
            -123.13981719713613,
            49.268298406977294
          ],
          [
            -123.13984142617718,
            49.26827230956508
          ],
          [
            -123.13986944129614,
            49.26824346402839
          ],
          [
            -123.13988525874544,
            49.26822256701956
          ],
          [
            -123.1399023911659,
            49.268195173881566
          ],
          [
            -123.13991788248563,
            49.268170760139554
          ],
          [
            -123.1399327272269,
            49.268146167274466
          ],
          [
            -123.13994692544148,
            49.268121413276816
          ],
          [
            -123.13996044966386,
            49.26809650717527
          ],
          [
            -123.13997329986958,
            49.26807143997502
          ],
          [
            -123.13998548988164,
            49.26804623864504
          ],
          [
            -123.13999700592976,
            49.26802089420701
          ],
          [
            -123.14000784806575,
            49.26799542465156
          ],
          [
            -123.14001800257022,
            49.26796983899061
          ],
          [
            -123.14057127415737,
            49.26593344494037
          ],
          [
            -123.14059909811574,
            49.26586212409319
          ],
          [
            -123.14063835542842,
            49.265775380537235
          ],
          [
            -123.14069769804809,
            49.26566093426598
          ],
          [
            -123.14075809832302,
            49.26555599460468
          ],
          [
            -123.14079571158697,
            49.265485813165355
          ],
          [
            -123.14082448197873,
            49.26542848764359
          ],
          [
            -123.14086355370237,
            49.26534440681124
          ],
          [
            -123.1409068428391,
            49.265245073948506
          ],
          [
            -123.1409289026027,
            49.2651867761046
          ],
          [
            -123.1409395542852,
            49.26515273425042
          ],
          [
            -123.14095348541629,
            49.265097423728974
          ],
          [
            -123.1409609320074,
            49.265057691817304
          ],
          [
            -123.14097009098958,
            49.26496770160216
          ],
          [
            -123.14098392003156,
            49.26454852612369
          ]
        ],
        "type": "LineString"
      },
      "properties": {}
    },
    "geo_point_2d": {
      "lon": -123.14038724550365,
      "lat": 49.26662636739607
    }
  },
  {
    "project": "E 20th Av - Clark Dr to Knight St",
    "street": null,
    "location": "E 20th Av - Clark Dr to Knight St",
    "comp_date": "2025-11-19",
    "url_link": "http://vanmapp1.vancouver.ca/roadahead/events/details/7a13bc14-9d74-4541-81cf-7f5fe2bbc51b",
    "geom": {
      "type": "Feature",
      "geometry": {
        "coordinates": [
          [
            -123.07796729750848,
            49.25262838289396
          ],
          [
            -123.07604061299644,
            49.252600436327214
          ]
        ],
        "type": "LineString"
      },
      "properties": {}
    },
    "geo_point_2d": {
      "lon": -123.07700395525245,
      "lat": 49.25261440961059
    }
  },
  {
    "project": "Dundas St - Cassiar St to Skeena St\r\nTriumph St - Cassiar St to Kootenay St\r\nPan",
    "street": null,
    "location": "Dundas St - Cassiar St to Skeena St\r\nTriumph St - Cassiar St to Kootenay St\r\nPan",
    "comp_date": "2025-12-05",
    "url_link": "http://vanmapp1.vancouver.ca/roadahead/events/details/85bf5084-b8cf-4410-bd22-b7fef0e4830f",
    "geom": {
      "type": "Feature",
      "geometry": {
        "coordinates": [
          [
            [
              -123.03090050473189,
              49.2847736394923
            ],
            [
              -123.02833094849562,
              49.28477713870129
            ]
          ],
          [
            [
              -123.03088246319862,
              49.2838690403606
            ],
            [
              -123.02571101721716,
              49.28386033482343
            ]
          ],
          [
            [
              -123.03090344086705,
              49.282973630735455
            ],
            [
              -123.02833476444256,
              49.28296613360547
            ]
          ]
        ],
        "type": "MultiLineString"
      },
      "properties": {}
    },
    "geo_point_2d": {
      "lon": -123.02895495034613,
      "lat": 49.2838687251026
    }
  },
  {
    "project": "W 1th Av from Dunbar St to Collingwood St",
    "street": null,
    "location": "W 1th Av from Dunbar St to Collingwood St",
    "comp_date": "2026-01-01",
    "url_link": "http://vanmapp1.vancouver.ca/roadahead/events/details/c78471a8-0098-47c4-980a-febc35e628ea",
    "geom": {
      "type": "Feature",
      "geometry": {
        "coordinates": [
          [
            -123.18191483577667,
            49.262492146466656
          ],
          [
            -123.18385071541186,
            49.26252337199773
          ]
        ],
        "type": "LineString"
      },
      "properties": {}
    },
    "geo_point_2d": {
      "lon": -123.18288277559427,
      "lat": 49.26250775923219
    }
  },
  {
    "project": "E 62nd Av - Knight St to Argyle St                  \r\nE 61st Av - Knight St to A",
    "street": null,
    "location": "E 62nd Av - Knight St to Argyle St                  \r\nE 61st Av - Knight St to A",
    "comp_date": "2026-01-21",
    "url_link": "http://vanmapp1.vancouver.ca/roadahead/events/details/e67c3a11-0ee9-40ef-a83d-8539840a6af1",
    "geom": {
      "type": "Feature",
      "geometry": {
        "coordinates": [
          [
            [
              -123.07711268128811,
              49.21378156602759
            ],
            [
              -123.07207605346363,
              49.21375532514034
            ]
          ],
          [
            [
              -123.07711937882875,
              49.21464750749172
            ],
            [
              -123.07204926330107,
              49.21460377350482
            ]
          ],
          [
            [
              -123.07707249543107,
              49.21547407382937
            ],
            [
              -123.07204926330107,
              49.215439087107825
            ]
          ],
          [
            [
              -123.07707249543107,
              49.21638809147794
            ],
            [
              -123.07442692610047,
              49.21640995758682
            ],
            [
              -123.074018370296,
              49.21631811930408
            ],
            [
              -123.0720425654538,
              49.21629625315461
            ]
          ],
          [
            [
              -123.07403127363992,
              49.21631535165608
            ],
            [
              -123.07406502790224,
              49.21375315493651
            ]
          ]
        ],
        "type": "MultiLineString"
      },
      "properties": {}
    },
    "geo_point_2d": {
      "lon": -123.07451483767278,
      "lat": 49.21504995764013
    }
  },
  {
    "project": "Alignment is along Highbury Street through Memorial West Park, between W 31st Av",
    "street": null,
    "location": "Alignment is along Highbury Street through Memorial West Park, between W 31st Av",
    "comp_date": "2026-02-01",
    "url_link": "http://vanmapp1.vancouver.ca/roadahead/events/details/9d7ad385-d4e0-46fb-8e14-7a40f958b1ef",
    "geom": {
      "type": "Feature",
      "geometry": {
        "coordinates": [
          [
            -123.18815934348683,
            49.24519436177815
          ],
          [
            -123.18817356592662,
            49.241433898919325
          ]
        ],
        "type": "LineString"
      },
      "properties": {}
    },
    "geo_point_2d": {
      "lon": -123.18816645470673,
      "lat": 49.243314130348736
    }
  },
  {
    "project": "Hemlock On-Ramp",
    "street": null,
    "location": "Hemlock On-Ramp",
    "comp_date": "2026-02-28",
    "url_link": "http://vanmapp1.vancouver.ca/roadahead/events/details/a44edc6f-a110-45dd-b5a6-f652404374c1",
    "geom": {
      "type": "Feature",
      "geometry": {
        "coordinates": [
          [
            -123.1376784668858,
            49.26953783310583
          ],
          [
            -123.13769203880359,
            49.2695196376375
          ],
          [
            -123.1376994608411,
            49.269509419242496
          ],
          [
            -123.13770873070314,
            49.26949635616208
          ],
          [
            -123.1377193823676,
            49.2694809346919
          ],
          [
            -123.1377294988749,
            49.2694658556762
          ],
          [
            -123.13773801262968,
            49.26945277550419
          ],
          [
            -123.137746758137,
            49.269439002424974
          ],
          [
            -123.13775669287139,
            49.26942282620922
          ],
          [
            -123.13776527168577,
            49.269408432658565
          ],
          [
            -123.13777421851114,
            49.26939291426859
          ],
          [
            -123.13778581703495,
            49.26937198660153
          ],
          [
            -123.13779630524039,
            49.26935218465712
          ],
          [
            -123.13780923746575,
            49.269326442965706
          ],
          [
            -123.13781485449326,
            49.2693147155224
          ],
          [
            -123.13782172762062,
            49.26929991921776
          ],
          [
            -123.13782641356192,
            49.26928950618341
          ],
          [
            -123.1378338301134,
            49.269272406458924
          ],
          [
            -123.13783828178867,
            49.269261786813956
          ],
          [
            -123.13784449333244,
            49.26924636163315
          ],
          [
            -123.13784746884035,
            49.26923876613557
          ],
          [
            -123.13785210839431,
            49.269226509139685
          ],
          [
            -123.13785704687726,
            49.26921300145432
          ],
          [
            -123.13786010192557,
            49.26920435342322
          ],
          [
            -123.13787372977237,
            49.269161888819326
          ],
          [
            -123.13787890554606,
            49.26914474678935
          ],
          [
            -123.13788290644521,
            49.269130223763995
          ],
          [
            -123.13788759821574,
            49.269112047863246
          ],
          [
            -123.13789117205296,
            49.26909719252478
          ],
          [
            -123.13789453922023,
            49.26908216652407
          ],
          [
            -123.13789782200355,
            49.26906645698881
          ],
          [
            -123.13790031543385,
            49.26905359087834
          ],
          [
            -123.13790349567289,
            49.26903561467509
          ],
          [
            -123.1379057253924,
            49.269021840364076
          ],
          [
            -123.13790758697517,
            49.26900914591627
          ],
          [
            -123.1379094721128,
            49.268995039194095
          ],
          [
            -123.13791195523781,
            49.268973546699556
          ],
          [
            -123.137913730987,
            49.26895471762819
          ],
          [
            -123.1379149112105,
            49.26893922648648
          ],
          [
            -123.1379161704803,
            49.268917573538886
          ],
          [
            -123.1379166973357,
            49.26890439494309
          ],
          [
            -123.137917129278,
            49.26888675484179
          ],
          [
            -123.13791797340063,
            49.26886904228681
          ],
          [
            -123.13791924237103,
            49.268850870469436
          ],
          [
            -123.13791989192744,
            49.26882253481614
          ],
          [
            -123.13791964810089,
            49.26880903331289
          ],
          [
            -123.1379185886764,
            49.268788957292344
          ],
          [
            -123.13791645046949,
            49.268766516821955
          ],
          [
            -123.13791519979483,
            49.26875673153776
          ],
          [
            -123.13791305734135,
            49.26874262962218
          ],
          [
            -123.13790923394711,
            49.2687221880972
          ],
          [
            -123.1379029881094,
            49.268695686698806
          ],
          [
            -123.13789707433028,
            49.26867488786016
          ],
          [
            -123.13789294220274,
            49.26866203865137
          ],
          [
            -123.13788906201721,
            49.26865080827767
          ],
          [
            -123.13788428395821,
            49.26863800481536
          ],
          [
            -123.13787813823237,
            49.26862275629054
          ],
          [
            -123.13787384928374,
            49.268612821712765
          ],
          [
            -123.13786852455186,
            49.26860115229724
          ],
          [
            -123.13786151514572,
            49.268586732360376
          ],
          [
            -123.13785221454164,
            49.2685689509519
          ],
          [
            -123.13784313859078,
            49.26855286037221
          ],
          [
            -123.1378270241987,
            49.26852672155442
          ],
          [
            -123.13781409075658,
            49.26850753222976
          ],
          [
            -123.13779673222861,
            49.26848380560506
          ],
          [
            -123.13776112013866,
            49.26844071608667
          ],
          [
            -123.13771270573821,
            49.26839093139711
          ],
          [
            -123.13765745063507,
            49.26834282794428
          ],
          [
            -123.13759465437887,
            49.26829661344206
          ],
          [
            -123.13752393449931,
            49.26825315187273
          ],
          [
            -123.13744507907344,
            49.268205427217595
          ],
          [
            -123.13736951654815,
            49.268160397153565
          ],
          [
            -123.13728983936475,
            49.268113644850445
          ],
          [
            -123.13720953107196,
            49.26806727103997
          ],
          [
            -123.13712768300063,
            49.268020755077515
          ],
          [
            -123.13704633277193,
            49.26797526391911
          ],
          [
            -123.13694671642467,
            49.2679205382928
          ],
          [
            -123.13684169313825,
            49.26786398396297
          ],
          [
            -123.13678346036477,
            49.26783214693788
          ],
          [
            -123.13670403737794,
            49.26778745382853
          ],
          [
            -123.13664833533913,
            49.2677560994816
          ],
          [
            -123.13659509772913,
            49.26772614544561
          ],
          [
            -123.13653388900399,
            49.267691703203894
          ],
          [
            -123.1365021970873,
            49.26767387617957
          ],
          [
            -123.13647130365996,
            49.26765648896827
          ],
          [
            -123.13644107106484,
            49.26763946977158
          ],
          [
            -123.13641546426062,
            49.2676250627091
          ],
          [
            -123.13638784747627,
            49.267609524618166
          ],
          [
            -123.1363589641229,
            49.26759326839928
          ],
          [
            -123.1363347232204,
            49.26758068573267
          ],
          [
            -123.13630607506461,
            49.267564968935034
          ],
          [
            -123.13627573053586,
            49.26754719422996
          ],
          [
            -123.13625933149645,
            49.26753706698338
          ],
          [
            -123.13623913073378,
            49.26752406575275
          ],
          [
            -123.13621530618028,
            49.26750791147509
          ],
          [
            -123.1361923467275,
            49.267491432345565
          ],
          [
            -123.13616510038602,
            49.26747059559085
          ],
          [
            -123.13614579948774,
            49.26745490371806
          ],
          [
            -123.1361158997448,
            49.26742887984685
          ],
          [
            -123.13610428255222,
            49.2674181262758
          ],
          [
            -123.13608362247473,
            49.26739801934963
          ],
          [
            -123.13607001699586,
            49.26738402084905
          ],
          [
            -123.13605770564166,
            49.26737075842945
          ],
          [
            -123.13604700594483,
            49.26735873544874
          ],
          [
            -123.1360374908494,
            49.267347610592395
          ],
          [
            -123.13602812629235,
            49.267336242687634
          ],
          [
            -123.13601653947299,
            49.2673215221879
          ],
          [
            -123.13600445368962,
            49.26730530007566
          ],
          [
            -123.13599500113665,
            49.26729191734648
          ],
          [
            -123.13598575375923,
            49.26727816557181
          ],
          [
            -123.1359766688869,
            49.26726352308012
          ],
          [
            -123.13596944222073,
            49.267249804906754
          ],
          [
            -123.13596302904465,
            49.26723699429104
          ],
          [
            -123.13595612975912,
            49.26722235822098
          ],
          [
            -123.13595104002127,
            49.2672109492988
          ],
          [
            -123.13594518735917,
            49.26719702261744
          ],
          [
            -123.13593798885061,
            49.26717853695186
          ],
          [
            -123.13593304374947,
            49.267164735134884
          ],
          [
            -123.13592840046046,
            49.267150717077755
          ],
          [
            -123.13592533543566,
            49.26714079897582
          ],
          [
            -123.13592133856291,
            49.26712691508595
          ],
          [
            -123.13591762943484,
            49.267112698034936
          ],
          [
            -123.13591399917482,
            49.26709716759157
          ],
          [
            -123.13591026484139,
            49.267078776796126
          ],
          [
            -123.13590679944254,
            49.26705820884533
          ],
          [
            -123.1359036101521,
            49.26703307100695
          ],
          [
            -123.13590163551108,
            49.267009766760935
          ],
          [
            -123.13590049951542,
            49.266976512834844
          ],
          [
            -123.13590501303811,
            49.26689324793418
          ],
          [
            -123.13590724777148,
            49.26680606380438
          ],
          [
            -123.13590913327658,
            49.26673186016123
          ],
          [
            -123.13591118217319,
            49.26665208829448
          ],
          [
            -123.13591362757963,
            49.26655653837443
          ],
          [
            -123.1359160840045,
            49.26645999896749
          ],
          [
            -123.13591743660433,
            49.26640196932169
          ],
          [
            -123.13592140105541,
            49.266349027887856
          ],
          [
            -123.13593016866461,
            49.26630328596053
          ],
          [
            -123.13594264432452,
            49.266261389616574
          ],
          [
            -123.13596050248788,
            49.266217436030956
          ],
          [
            -123.13597781075507,
            49.26618346776519
          ],
          [
            -123.13600026554471,
            49.26614660597863
          ]
        ],
        "type": "LineString"
      },
      "properties": {}
    },
    "geo_point_2d": {
      "lon": -123.13688065967763,
      "lat": 49.26786832232676
    }
  },
  {
    "project": "Various Locations",
    "street": null,
    "location": "Various Locations",
    "comp_date": "2026-04-01",
    "url_link": "http://vanmapp1.vancouver.ca/roadahead/events/details/1cbc4ee7-698c-4ceb-bcc7-9c9d5c2814d5",
    "geom": {
      "type": "Feature",
      "geometry": {
        "coordinates": [
          [
            [
              -123.10296232191241,
              49.26331509000124
            ],
            [
              -123.10297621915663,
              49.26296573076257
            ]
          ],
          [
            [
              -123.10297621915663,
              49.26296573076257
            ],
            [
              -123.10299604033806,
              49.26253066887506
            ]
          ],
          [
            [
              -123.11291515457648,
              49.263187640128876
            ],
            [
              -123.11293345949241,
              49.26268651720608
            ]
          ],
          [
            [
              -123.11491784815064,
              49.262718004765446
            ],
            [
              -123.11753622444502,
              49.262760158011474
            ]
          ],
          [
            [
              -123.12418833376523,
              49.26385173035064
            ],
            [
              -123.12420590913786,
              49.26337366117119
            ]
          ],
          [
            [
              -123.12420590913786,
              49.26337366117119
            ],
            [
              -123.12422466571381,
              49.26286802036566
            ]
          ],
          [
            [
              -123.14812689528398,
              49.26423539325219
            ],
            [
              -123.14814539417256,
              49.26375735519022
            ]
          ]
        ],
        "type": "MultiLineString"
      },
      "properties": {}
    },
    "geo_point_2d": {
      "lon": -123.11828769589711,
      "lat": 49.26301034265017
    }
  },
  {
    "project": "Between Oak Street (west) and Hudson Street (east), from the south side of the W",
    "street": null,
    "location": "Between Oak Street (west) and Hudson Street (east), from the south side of the W",
    "comp_date": "2026-04-30",
    "url_link": "http://vanmapp1.vancouver.ca/roadahead/events/details/7ed4d284-aef8-48c2-8e07-cb12f97a7f20",
    "geom": {
      "type": "Feature",
      "geometry": {
        "coordinates": [
          [
            [
              -123.12838026777656,
              49.24586828976922
            ],
            [
              -123.12926857275839,
              49.2458810979318
            ]
          ],
          [
            [
              -123.12925213047927,
              49.246335375667826
            ],
            [
              -123.12926857275839,
              49.2458810979318
            ]
          ],
          [
            [
              -123.12923550838973,
              49.246794573959335
            ],
            [
              -123.12925213047927,
              49.246335375667826
            ]
          ],
          [
            [
              -123.12836489843437,
              49.246320884076624
            ],
            [
              -123.12838026777656,
              49.24586828976922
            ]
          ],
          [
            [
              -123.12834928506139,
              49.24678015308055
            ],
            [
              -123.12836489843437,
              49.246320884076624
            ]
          ],
          [
            [
              -123.12834928506139,
              49.24678015308055
            ],
            [
              -123.12923550838973,
              49.246794573959335
            ]
          ],
          [
            [
              -123.12833359537797,
              49.247241895819286
            ],
            [
              -123.12834928506139,
              49.24678015308055
            ]
          ],
          [
            [
              -123.13060377233911,
              49.24727823814905
            ],
            [
              -123.13062039048387,
              49.24681708773451
            ]
          ],
          [
            [
              -123.12921880956934,
              49.247256075077075
            ],
            [
              -123.12923550838973,
              49.246794573959335
            ]
          ],
          [
            [
              -123.12921880956934,
              49.247256075077075
            ],
            [
              -123.12990070361347,
              49.24726698619082
            ]
          ],
          [
            [
              -123.12920216031333,
              49.247715624134514
            ],
            [
              -123.12921880956934,
              49.247256075077075
            ]
          ],
          [
            [
              -123.12990070361347,
              49.24726698619082
            ],
            [
              -123.13060377233911,
              49.24727823814905
            ]
          ],
          [
            [
              -123.1305871916027,
              49.24773805718749
            ],
            [
              -123.13060377233911,
              49.24727823814905
            ]
          ],
          [
            [
              -123.13205513626171,
              49.24776183612133
            ],
            [
              -123.13207215605136,
              49.24730173751601
            ]
          ],
          [
            [
              -123.1305871916027,
              49.24773805718749
            ],
            [
              -123.13205513626171,
              49.24776183612133
            ]
          ],
          [
            [
              -123.13057059803619,
              49.248198334958005
            ],
            [
              -123.1305871916027,
              49.24773805718749
            ]
          ],
          [
            [
              -123.13205513626171,
              49.24776183612133
            ],
            [
              -123.13441267765032,
              49.247799973673125
            ]
          ],
          [
            [
              -123.13062039048387,
              49.24681708773451
            ],
            [
              -123.13208917373356,
              49.24684096423118
            ]
          ],
          [
            [
              -123.13208917373356,
              49.24684096423118
            ],
            [
              -123.13444521518551,
              49.24687921976519
            ]
          ],
          [
            [
              -123.13065340883833,
              49.2459010567122
            ],
            [
              -123.13067009105492,
              49.245438493855374
            ]
          ],
          [
            [
              -123.13063694501557,
              49.24635797927061
            ],
            [
              -123.13065340883833,
              49.2459010567122
            ]
          ],
          [
            [
              -123.13062039048387,
              49.24681708773451
            ],
            [
              -123.13063694501557,
              49.24635797927061
            ]
          ],
          [
            [
              -123.12925213047927,
              49.246335375667826
            ],
            [
              -123.12993497425019,
              49.246346519390954
            ]
          ],
          [
            [
              -123.12926857275839,
              49.2458810979318
            ],
            [
              -123.12928541147775,
              49.245415638636075
            ]
          ],
          [
            [
              -123.13065340883833,
              49.2459010567122
            ],
            [
              -123.13212313324763,
              49.24592223313826
            ]
          ],
          [
            [
              -123.13212655512521,
              49.245829803185615
            ],
            [
              -123.13320041189225,
              49.2459231999413
            ],
            [
              -123.134334638798,
              49.24612568270348
            ],
            [
              -123.13447172250747,
              49.2461567816658
            ]
          ]
        ],
        "type": "MultiLineString"
      },
      "properties": {}
    },
    "geo_point_2d": {
      "lon": -123.13113681456431,
      "lat": 49.24678274789856
    }
  },
  {
    "project": "Bayswater St between W 6th and W 7th Av",
    "street": null,
    "location": "Bayswater St between W 6th and W 7th Av",
    "comp_date": "2026-06-24",
    "url_link": "http://vanmapp1.vancouver.ca/roadahead/events/details/98cda8a2-a5e8-41b7-af15-c4cfb742076e",
    "geom": {
      "type": "Feature",
      "geometry": {
        "coordinates": [
          [
            -123.17114447861454,
            49.266648939185586
          ],
          [
            -123.17117232799235,
            49.26587474197456
          ]
        ],
        "type": "LineString"
      },
      "properties": {}
    },
    "geo_point_2d": {
      "lon": -123.17115840330345,
      "lat": 49.26626184058007
    }
  },
  {
    "project": "E 22nd Ave from Welwyn to Commercial St",
    "street": null,
    "location": "E 22nd Ave from Welwyn to Commercial St",
    "comp_date": "2026-06-26",
    "url_link": "http://vanmapp1.vancouver.ca/roadahead/events/details/9bcb9dfb-2439-43f4-b227-8ea369d577c7",
    "geom": {
      "type": "Feature",
      "geometry": {
        "coordinates": [
          [
            -123.06943131525497,
            49.25034743334149
          ],
          [
            -123.06813714219895,
            49.25032458541489
          ]
        ],
        "type": "LineString"
      },
      "properties": {}
    },
    "geo_point_2d": {
      "lon": -123.06878422872697,
      "lat": 49.250336009378195
    }
  },
  {
    "project": null,
    "street": null,
    "location": null,
    "comp_date": "2027-01-16",
    "url_link": "http://vanmapp1.vancouver.ca/roadahead/events/details/569cde2e-876f-4ecb-b13b-86beeeeadbd9",
    "geom": {
      "type": "Feature",
      "geometry": {
        "coordinates": [
          [
            -123.0249236046173,
            49.29248448897795
          ],
          [
            -123.0249287401899,
            49.292528032815255
          ],
          [
            -123.02412764229045,
            49.29268211065113
          ],
          [
            -123.02412764229045,
            49.29263856694996
          ],
          [
            -123.0249236046173,
            49.29248448897795
          ]
        ],
        "type": "LineString"
      },
      "properties": {}
    },
    "geo_point_2d": {
      "lon": -123.02452698146213,
      "lat": 49.29258335033243
    }
  },
  {
    "project": null,
    "street": null,
    "location": null,
    "comp_date": "2028-01-02",
    "url_link": "http://vanmapp1.vancouver.ca/roadahead/events/details/3d8e433d-215c-4c98-acdf-1f504e12625f",
    "geom": {
      "type": "Feature",
      "geometry": {
        "coordinates": [
          [
            -123.08745717210368,
            49.27646261947456
          ],
          [
            -123.08731300897043,
            49.276458856839696
          ],
          [
            -123.08731877585898,
            49.27641370673874
          ],
          [
            -123.08746293826577,
            49.27641370673874
          ],
          [
            -123.08745717210368,
            49.27646261947456
          ]
        ],
        "type": "LineString"
      },
      "properties": {}
    },
    "geo_point_2d": {
      "lon": -123.08738867600971,
      "lat": 49.27643723467438
    }
  }
]
