[
  {
    "project": "W 28th Av from Camosun St to Crown St",
    "street": null,
    "location": "W 28th Av from Camosun St to Crown St",
    "comp_date": "2024-11-29",
    "url_link": "http://vanmapp1.vancouver.ca/roadahead/events/details/0fa59b3b-1e0f-42b7-bc75-32f96dffe621",
    "geom": {
      "type": "Feature",
      "geometry": {
        "coordinates": [
          [
            -123.19361848944565,
            49.24715800038376
          ],
          [
            -123.19675482069512,
            49.24717104288729
          ]
        ],
        "type": "LineString"
      },
      "properties": {}
    },
    "geo_point_2d": {
      "lon": -123.19518665507037,
      "lat": 49.247164521635526
    }
  },
  {
    "project": "Both sides 400 block of E 19th Av from West PL of 409 to East PL of 451.",
    "street": null,
    "location": "Both sides 400 block of E 19th Av from West PL of 409 to East PL of 451.",
    "comp_date": "2024-11-29",
    "url_link": "http://vanmapp1.vancouver.ca/roadahead/events/details/7349e1d7-3202-4ec2-9548-3a48a7bb4da8",
    "geom": {
      "type": "Feature",
      "geometry": {
        "coordinates": [
          [
            -123.09480198760163,
            49.2538064702282
          ],
          [
            -123.09591778655185,
            49.25381697444564
          ]
        ],
        "type": "LineString"
      },
      "properties": {}
    },
    "geo_point_2d": {
      "lon": -123.09535988707674,
      "lat": 49.25381172233692
    }
  },
  {
    "project": "Windermere St from E 7th Av to E 8th Av",
    "street": null,
    "location": "Windermere St from E 7th Av to E 8th Av",
    "comp_date": "2024-11-29",
    "url_link": "http://vanmapp1.vancouver.ca/roadahead/events/details/7e7d2a17-3c6e-49e3-8061-56ebbb2a7068",
    "geom": {
      "type": "Feature",
      "geometry": {
        "coordinates": [
          [
            [
              -123.03649612687866,
              49.26383092010147
            ],
            [
              -123.03650069969753,
              49.26337804611737
            ]
          ],
          [
            [
              -123.03650069969753,
              49.26337804611737
            ],
            [
              -123.03650431059053,
              49.26292553220955
            ]
          ]
        ],
        "type": "MultiLineString"
      },
      "properties": {}
    },
    "geo_point_2d": {
      "lon": -123.03650045838279,
      "lat": 49.263378228321564
    }
  },
  {
    "project": "W 27th Av from Collingwood St to Blenheim St",
    "street": null,
    "location": "W 27th Av from Collingwood St to Blenheim St",
    "comp_date": "2024-11-29",
    "url_link": "http://vanmapp1.vancouver.ca/roadahead/events/details/d9137866-504b-4fdb-9e1d-cf499b88c7d1",
    "geom": {
      "type": "Feature",
      "geometry": {
        "coordinates": [
          [
            [
              -123.18126440464864,
              49.248052381069584
            ],
            [
              -123.18180682450586,
              49.24805438924071
            ]
          ],
          [
            [
              -123.17924569207646,
              49.24804479941619
            ],
            [
              -123.18126440464864,
              49.248052381069584
            ]
          ],
          [
            [
              -123.17860524839084,
              49.24804259797858
            ],
            [
              -123.17924569207646,
              49.24804479941619
            ]
          ]
        ],
        "type": "MultiLineString"
      },
      "properties": {}
    },
    "geo_point_2d": {
      "lon": -123.18020603669673,
      "lat": 49.2480484241057
    }
  },
  {
    "project": "Shaughnessy St from Park Dr to W 64th Av",
    "street": null,
    "location": "Shaughnessy St from Park Dr to W 64th Av",
    "comp_date": "2024-11-29",
    "url_link": "http://vanmapp1.vancouver.ca/roadahead/events/details/0eea739f-3a55-402e-a74b-4086dab6fc33",
    "geom": {
      "type": "Feature",
      "geometry": {
        "coordinates": [
          [
            [
              -123.12867799276945,
              49.214067610720804
            ],
            [
              -123.12869748901939,
              49.21349047850069
            ]
          ],
          [
            [
              -123.12869748901939,
              49.21349047850069
            ],
            [
              -123.12871514780728,
              49.21296733797516
            ]
          ]
        ],
        "type": "MultiLineString"
      },
      "properties": {}
    },
    "geo_point_2d": {
      "lon": -123.12869657383933,
      "lat": 49.213517474467885
    }
  },
  {
    "project": "Park Dr from Fremlin St to Oak St",
    "street": null,
    "location": "Park Dr from Fremlin St to Oak St",
    "comp_date": "2024-11-29",
    "url_link": "http://vanmapp1.vancouver.ca/roadahead/events/details/1e6b4336-aeeb-4c8f-b8cd-f84794a33de3",
    "geom": {
      "type": "Feature",
      "geometry": {
        "coordinates": [
          [
            [
              -123.12934695198106,
              49.21425871499184
            ],
            [
              -123.13004695791861,
              49.21445868576524
            ]
          ],
          [
            [
              -123.12867799276945,
              49.214067610720804
            ],
            [
              -123.12934695198106,
              49.21425871499184
            ]
          ]
        ],
        "type": "MultiLineString"
      },
      "properties": {}
    },
    "geo_point_2d": {
      "lon": -123.12936247516717,
      "lat": 49.214263148862166
    }
  },
  {
    "project": "Both sides of 1000-1200 Block Nootka St from Lane North of Charles St to North o",
    "street": null,
    "location": "Both sides of 1000-1200 Block Nootka St from Lane North of Charles St to North o",
    "comp_date": "2024-11-29",
    "url_link": "http://vanmapp1.vancouver.ca/roadahead/events/details/25e00b3c-378d-48f4-9917-3ece9938b79d",
    "geom": {
      "type": "Feature",
      "geometry": {
        "coordinates": [
          [
            -123.04142554514395,
            49.273760966464806
          ],
          [
            -123.04141481630788,
            49.27420896322187
          ]
        ],
        "type": "LineString"
      },
      "properties": {}
    },
    "geo_point_2d": {
      "lon": -123.04142018072591,
      "lat": 49.273984964843336
    }
  },
  {
    "project": "Both Sides of 3100 Block of E Georgia Street From West PL of 3128 to East PL of",
    "street": null,
    "location": "Both Sides of 3100 Block of E Georgia Street From West PL of 3128 to East PL of",
    "comp_date": "2024-11-29",
    "url_link": "http://vanmapp1.vancouver.ca/roadahead/events/details/4e7705dd-ef61-4568-942f-b960d9345741",
    "geom": {
      "type": "Feature",
      "geometry": {
        "coordinates": [
          [
            -123.03800017869422,
            49.27825990133198
          ],
          [
            -123.0362843556748,
            49.27825990133198
          ]
        ],
        "type": "LineString"
      },
      "properties": {}
    },
    "geo_point_2d": {
      "lon": -123.0371422671845,
      "lat": 49.27825990133198
    }
  },
  {
    "project": "W 68th Av from Heather St to Ash St",
    "street": null,
    "location": "W 68th Av from Heather St to Ash St",
    "comp_date": "2024-11-29",
    "url_link": "http://vanmapp1.vancouver.ca/roadahead/events/details/8378dcdf-a143-4808-a1df-1f9850343658",
    "geom": {
      "type": "Feature",
      "geometry": {
        "coordinates": [
          [
            -123.12027948189551,
            49.21022376394788
          ],
          [
            -123.12413487179153,
            49.21027393554684
          ]
        ],
        "type": "LineString"
      },
      "properties": {}
    },
    "geo_point_2d": {
      "lon": -123.12220717684352,
      "lat": 49.21024884974736
    }
  },
  {
    "project": "Both sides of 3400 block of Napier St from West PL of 3455 to the East PL of 349",
    "street": null,
    "location": "Both sides of 3400 block of Napier St from West PL of 3455 to the East PL of 349",
    "comp_date": "2024-12-03",
    "url_link": "http://vanmapp1.vancouver.ca/roadahead/events/details/3dc2b8f4-84de-4a72-8bff-1694bde6b6b7",
    "geom": {
      "type": "Feature",
      "geometry": {
        "coordinates": [
          [
            -123.02938427491956,
            49.274944280995584
          ],
          [
            -123.02844013734634,
            49.274944280995584
          ]
        ],
        "type": "LineString"
      },
      "properties": {}
    },
    "geo_point_2d": {
      "lon": -123.02891220613296,
      "lat": 49.274944280995584
    }
  },
  {
    "project": "Both sides of 2100 Block E 42nd Ave from West of PL 2136 to East of PL 2196.",
    "street": null,
    "location": "Both sides of 2100 Block E 42nd Ave from West of PL 2136 to East of PL 2196.",
    "comp_date": "2024-12-03",
    "url_link": "http://vanmapp1.vancouver.ca/roadahead/events/details/819ab485-a572-40e3-a399-a47f7aff8c22",
    "geom": {
      "type": "Feature",
      "geometry": {
        "coordinates": [
          [
            -123.06233868276495,
            49.23206299473776
          ],
          [
            -123.06334182893652,
            49.23205248589187
          ]
        ],
        "type": "LineString"
      },
      "properties": {}
    },
    "geo_point_2d": {
      "lon": -123.06284025585073,
      "lat": 49.232057740314815
    }
  },
  {
    "project": "Both Sides of 5000 Block of Prince Edward Street From E 35th Avenue to E 34th Av",
    "street": null,
    "location": "Both Sides of 5000 Block of Prince Edward Street From E 35th Avenue to E 34th Av",
    "comp_date": "2024-12-04",
    "url_link": "http://vanmapp1.vancouver.ca/roadahead/events/details/d351c600-a9ba-40a7-8c0b-aa7651089614",
    "geom": {
      "type": "Feature",
      "geometry": {
        "coordinates": [
          [
            -123.09697945611605,
            49.23961346145319
          ],
          [
            -123.09700091378818,
            49.23886744188644
          ]
        ],
        "type": "LineString"
      },
      "properties": {}
    },
    "geo_point_2d": {
      "lon": -123.09699018495212,
      "lat": 49.239240451669815
    }
  },
  {
    "project": null,
    "street": null,
    "location": null,
    "comp_date": "2024-12-08",
    "url_link": "http://vanmapp1.vancouver.ca/roadahead/events/details/5d4f7918-9ea8-49e0-88be-6b1bfb01642b",
    "geom": {
      "type": "Feature",
      "geometry": {
        "coordinates": [
          [
            [
              -123.12085660665308,
              49.28825507986997
            ],
            [
              -123.11866035299187,
              49.287614065815376
            ]
          ],
          [
            [
              -123.11977468373367,
              49.28795150412179
            ],
            [
              -123.11913768433953,
              49.28837277997698
            ]
          ]
        ],
        "type": "MultiLineString"
      },
      "properties": {}
    },
    "geo_point_2d": {
      "lon": -123.11968282612783,
      "lat": 49.28799152517901
    }
  },
  {
    "project": "Fleming St from E 37th Av to E 39th Av",
    "street": null,
    "location": "Fleming St from E 37th Av to E 39th Av",
    "comp_date": "2024-12-13",
    "url_link": "http://vanmapp1.vancouver.ca/roadahead/events/details/49b9d48e-a29c-48bd-8f43-c22dc30ff025",
    "geom": {
      "type": "Feature",
      "geometry": {
        "coordinates": [
          [
            [
              -123.0727786366854,
              49.23637680346374
            ],
            [
              -123.0728242680779,
              49.234748814604444
            ]
          ],
          [
            [
              -123.07276145081562,
              49.236806445278944
            ],
            [
              -123.0727786366854,
              49.23637680346374
            ]
          ]
        ],
        "type": "MultiLineString"
      },
      "properties": {}
    },
    "geo_point_2d": {
      "lon": -123.07279489201863,
      "lat": 49.23577769907691
    }
  },
  {
    "project": "Dumfries St from Lane south of E 37th Av to E 39th Av",
    "street": null,
    "location": "Dumfries St from Lane south of E 37th Av to E 39th Av",
    "comp_date": "2024-12-20",
    "url_link": "http://vanmapp1.vancouver.ca/roadahead/events/details/950a374b-63db-4bb0-b377-97c4cfc3c130",
    "geom": {
      "type": "Feature",
      "geometry": {
        "coordinates": [
          [
            -123.07414952080866,
            49.23640946597283
          ],
          [
            -123.07420211439567,
            49.23476416524147
          ]
        ],
        "type": "LineString"
      },
      "properties": {}
    },
    "geo_point_2d": {
      "lon": -123.07417581760217,
      "lat": 49.23558681560715
    }
  },
  {
    "project": "W 10th Ave (Yew St to Cypress St)\r\nW 7th Ave (Yew St to Cypress St)",
    "street": null,
    "location": "W 10th Ave (Yew St to Cypress St)\r\nW 7th Ave (Yew St to Cypress St)",
    "comp_date": "2025-01-01",
    "url_link": "http://vanmapp1.vancouver.ca/roadahead/events/details/71fbc294-bb79-4fb3-9bb6-a76d100118e4",
    "geom": {
      "type": "Feature",
      "geometry": {
        "coordinates": [
          [
            -123.15534939644594,
            49.26290658986835
          ],
          [
            -123.15382360977375,
            49.26288333673111
          ],
          [
            -123.15297987536017,
            49.26286825656257
          ],
          [
            -123.15227593311229,
            49.262856728088195
          ],
          [
            -123.15058020367758,
            49.26283022879312
          ],
          [
            -123.14817942044908,
            49.262791540936604
          ],
          [
            -123.14816409923601,
            49.26325189042859
          ],
          [
            -123.14814539417256,
            49.26375735519022
          ],
          [
            -123.14812689528398,
            49.26423539325219
          ],
          [
            -123.14811051511163,
            49.264668290607545
          ],
          [
            -123.14807974753339,
            49.265506710248786
          ],
          [
            -123.15047888829062,
            49.2655450695182
          ],
          [
            -123.1528775934756,
            49.265583595433384
          ],
          [
            -123.155247491559,
            49.26562181341876
          ]
        ],
        "type": "LineString"
      },
      "properties": {}
    },
    "geo_point_2d": {
      "lon": -123.15114314223422,
      "lat": 49.264197330553955
    }
  },
  {
    "project": "E 6th Av - Windermere St to Rupert St\\t            \r\nWindermere St - E 5th Av to",
    "street": null,
    "location": "E 6th Av - Windermere St to Rupert St\\t            \r\nWindermere St - E 5th Av to",
    "comp_date": "2025-01-03",
    "url_link": "http://vanmapp1.vancouver.ca/roadahead/events/details/d7490cc3-9749-4b7c-afde-d3f962ee1e8c",
    "geom": {
      "type": "Feature",
      "geometry": {
        "coordinates": [
          [
            [
              -123.03649805514345,
              49.2651930108195
            ],
            [
              -123.03650271110962,
              49.26474089249274
            ]
          ],
          [
            [
              -123.04156102693383,
              49.264758793340434
            ],
            [
              -123.03903086501592,
              49.264749637061556
            ]
          ],
          [
            [
              -123.036500262164,
              49.26568812400441
            ],
            [
              -123.03649805514345,
              49.2651930108195
            ]
          ],
          [
            [
              -123.0495436959967,
              49.26477496525732
            ],
            [
              -123.04431691465969,
              49.26476997869088
            ]
          ],
          [
            [
              -123.04429119263114,
              49.264768150543745
            ],
            [
              -123.04353110893598,
              49.26476571385095
            ]
          ],
          [
            [
              -123.04353110893598,
              49.26476571385095
            ],
            [
              -123.04156102693383,
              49.264758793340434
            ]
          ],
          [
            [
              -123.04431176951252,
              49.262971581785706
            ],
            [
              -123.03101786377984,
              49.262920704157835
            ]
          ],
          [
            [
              -123.03903404831173,
              49.263857709963105
            ],
            [
              -123.03903404831173,
              49.262958373076145
            ]
          ],
          [
            [
              -123.03651933222142,
              49.26384249280778
            ],
            [
              -123.03650239217212,
              49.2647268594101
            ]
          ],
          [
            [
              -123.03903086501592,
              49.264749637061556
            ],
            [
              -123.03650271110962,
              49.26474089249274
            ]
          ],
          [
            [
              -123.03298763729669,
              49.263829458791946
            ],
            [
              -123.03903404831173,
              49.263857709963105
            ]
          ],
          [
            [
              -123.0345217174447,
              49.264733711479465
            ],
            [
              -123.033762253404,
              49.264731435217726
            ]
          ],
          [
            [
              -123.03650271110962,
              49.26474089249274
            ],
            [
              -123.0345217174447,
              49.264733711479465
            ]
          ],
          [
            [
              -123.03648603460017,
              49.262929592760685
            ],
            [
              -123.0364741606871,
              49.261929989700576
            ]
          ]
        ],
        "type": "MultiLineString"
      },
      "properties": {}
    },
    "geo_point_2d": {
      "lon": -123.03897035546358,
      "lat": 49.263904089013906
    }
  },
  {
    "project": "E 24th Av - Prince Edward St to St George St\r\nE 24th Av - Carolina St to Fraser",
    "street": null,
    "location": "E 24th Av - Prince Edward St to St George St\r\nE 24th Av - Carolina St to Fraser",
    "comp_date": "2025-02-07",
    "url_link": "http://vanmapp1.vancouver.ca/roadahead/events/details/f08f2569-9587-48ae-94fe-a858786e6916",
    "geom": {
      "type": "Feature",
      "geometry": {
        "coordinates": [
          [
            [
              -123.09387547854405,
              49.25469861733043
            ],
            [
              -123.09389579288475,
              49.2510389640195
            ]
          ],
          [
            [
              -123.09449773374766,
              49.251084419015854
            ],
            [
              -123.09452332821314,
              49.25018642733778
            ]
          ],
          [
            [
              -123.09675245840194,
              49.249328722740614
            ],
            [
              -123.09405224229359,
              49.24927860092285
            ]
          ],
          [
            [
              -123.09210346735965,
              49.249235790454634
            ],
            [
              -123.09016864701034,
              49.24920421563448
            ]
          ],
          [
            [
              -123.09202671349055,
              49.25194535093735
            ],
            [
              -123.090051584384,
              49.251934826577155
            ]
          ]
        ],
        "type": "MultiLineString"
      },
      "properties": {}
    },
    "geo_point_2d": {
      "lon": -123.09332288380898,
      "lat": 49.25103069508655
    }
  },
  {
    "project": "100 Block Terminal Avenue",
    "street": null,
    "location": "100 Block Terminal Avenue",
    "comp_date": "2025-03-01",
    "url_link": "https://vancouver.ca/streets-transportation/terminal-avenue-sewer-repairs.aspx",
    "geom": {
      "type": "Feature",
      "geometry": {
        "coordinates": [
          [
            -123.10163182687499,
            49.27294563042844
          ],
          [
            -123.10103090141138,
            49.27289498373639
          ],
          [
            -123.1004577110221,
            49.27280816067659
          ],
          [
            -123.1001359852083,
            49.272755102049985
          ]
        ],
        "type": "LineString"
      },
      "properties": {}
    },
    "geo_point_2d": {
      "lon": -123.10088224206491,
      "lat": 49.27286392941384
    }
  },
  {
    "project": "Roadway improvements at 1200-1300 Block of Bidwell b/w Beach & Davie. Geometric",
    "street": null,
    "location": "Roadway improvements at 1200-1300 Block of Bidwell b/w Beach & Davie. Geometric",
    "comp_date": "2025-04-05",
    "url_link": "https://vancouver.ca/streets-transportation/improving-bus-stops.aspx",
    "geom": {
      "type": "Feature",
      "geometry": {
        "coordinates": [
          [
            [
              -123.13274638717492,
              49.27537936969799
            ],
            [
              -123.13181536867882,
              49.27476817419776
            ]
          ],
          [
            [
              -123.14278256797127,
              49.284562816914985
            ],
            [
              -123.14024547041082,
              49.286247971126784
            ]
          ],
          [
            [
              -123.13811481404825,
              49.28068540102444
            ],
            [
              -123.13440176698383,
              49.278280786909306
            ]
          ]
        ],
        "type": "MultiLineString"
      },
      "properties": {}
    },
    "geo_point_2d": {
      "lon": -123.13760720912488,
      "lat": 49.28101250466326
    }
  },
  {
    "project": "Oak St On-ramp from Marine Drive",
    "street": null,
    "location": "Oak St On-ramp from Marine Drive",
    "comp_date": "2025-05-02",
    "url_link": "http://vanmapp1.vancouver.ca/roadahead/events/details/365bacdf-6c40-4100-b24a-455324f1bd68",
    "geom": {
      "type": "Feature",
      "geometry": {
        "coordinates": [
          [
            -123.12843829437679,
            49.2055288456244
          ],
          [
            -123.12841057040337,
            49.20561759833268
          ],
          [
            -123.1284410672489,
            49.20572446355516
          ],
          [
            -123.1284050251503,
            49.20566650293384
          ],
          [
            -123.12829690032791,
            49.20562665484695
          ],
          [
            -123.12819986453826,
            49.20561578698684
          ],
          [
            -123.12811946450789,
            49.2056429562048
          ],
          [
            -123.12820540930022,
            49.20561759833268
          ],
          [
            -123.12829967238146,
            49.20563389980046
          ],
          [
            -123.128393935299,
            49.20566469148284
          ],
          [
            -123.12843829437679,
            49.20572265232022
          ],
          [
            -123.12852146760672,
            49.20587661037092
          ],
          [
            -123.12866157481491,
            49.20600546882426
          ],
          [
            -123.12888004461745,
            49.206105957991866
          ],
          [
            -123.12917115084035,
            49.206167540749504
          ],
          [
            -123.12936183785398,
            49.20614855458666
          ],
          [
            -123.12957531577263,
            49.20611232943676
          ],
          [
            -123.1297111655507,
            49.20606704782841
          ],
          [
            -123.1298636497783,
            49.20604893528042
          ],
          [
            -123.12996068507681,
            49.20607067038
          ],
          [
            -123.13004663085144,
            49.206144932040786
          ],
          [
            -123.13009376231021,
            49.20624998496143
          ]
        ],
        "type": "LineString"
      },
      "properties": {}
    },
    "geo_point_2d": {
      "lon": -123.12894659997447,
      "lat": 49.205929032188706
    }
  },
  {
    "project": "Argyle St - E 32nd Av to E 33rd Av \\t         \r\nDumfries St - 5356 Dumfries St to",
    "street": null,
    "location": "Argyle St - E 32nd Av to E 33rd Av \\t         \r\nDumfries St - 5356 Dumfries St to",
    "comp_date": "2025-06-03",
    "url_link": "http://vanmapp1.vancouver.ca/roadahead/events/details/c3409c7d-2ea9-4d46-b0ff-0640e466ab2a",
    "geom": {
      "type": "Feature",
      "geometry": {
        "coordinates": [
          [
            [
              -123.06853355261237,
              49.24010131373973
            ],
            [
              -123.0685846455093,
              49.23749931547866
            ]
          ],
          [
            [
              -123.07133164888158,
              49.238455064321045
            ],
            [
              -123.07136383538975,
              49.23761796092745
            ]
          ],
          [
            [
              -123.07413187509313,
              49.237663494112894
            ],
            [
              -123.07137456422582,
              49.23762496603564
            ]
          ],
          [
            [
              -123.0741104174209,
              49.23850059673475
            ],
            [
              -123.0713370132995,
              49.23845856681592
            ]
          ],
          [
            [
              -123.074064906268,
              49.23934549158258
            ],
            [
              -123.0654001974905,
              49.2392484101602
            ]
          ],
          [
            [
              -123.07083980826012,
              49.24162120145289
            ],
            [
              -123.07089881685845,
              49.240146454171736
            ]
          ],
          [
            [
              -123.07133068613992,
              49.23844249394392
            ],
            [
              -123.06546201281533,
              49.238351428967405
            ]
          ],
          [
            [
              -123.0700627323123,
              49.234726673936706
            ],
            [
              -123.07014856300077,
              49.232645212625386
            ]
          ],
          [
            [
              -123.07422038799042,
              49.234763296647515
            ],
            [
              -123.07006296401741,
              49.23472826906735
            ]
          ],
          [
            [
              -123.0727731233691,
              49.236799193374594
            ],
            [
              -123.07283574242724,
              49.234754422363665
            ]
          ],
          [
            [
              -123.07417747264618,
              49.236090823626256
            ],
            [
              -123.07422038799042,
              49.234763296647515
            ]
          ]
        ],
        "type": "MultiLineString"
      },
      "properties": {}
    },
    "geo_point_2d": {
      "lon": -123.07065086072781,
      "lat": 49.23770531751831
    }
  },
  {
    "project": "Various Locations",
    "street": null,
    "location": "Various Locations",
    "comp_date": "2026-04-01",
    "url_link": "http://vanmapp1.vancouver.ca/roadahead/events/details/1cbc4ee7-698c-4ceb-bcc7-9c9d5c2814d5",
    "geom": {
      "type": "Feature",
      "geometry": {
        "coordinates": [
          [
            [
              -123.10296232191241,
              49.26331509000124
            ],
            [
              -123.10297621915663,
              49.26296573076257
            ]
          ],
          [
            [
              -123.10297621915663,
              49.26296573076257
            ],
            [
              -123.10299604033806,
              49.26253066887506
            ]
          ],
          [
            [
              -123.11291515457648,
              49.263187640128876
            ],
            [
              -123.11293345949241,
              49.26268651720608
            ]
          ],
          [
            [
              -123.11491784815064,
              49.262718004765446
            ],
            [
              -123.11753622444502,
              49.262760158011474
            ]
          ],
          [
            [
              -123.12418833376523,
              49.26385173035064
            ],
            [
              -123.12420590913786,
              49.26337366117119
            ]
          ],
          [
            [
              -123.12420590913786,
              49.26337366117119
            ],
            [
              -123.12422466571381,
              49.26286802036566
            ]
          ],
          [
            [
              -123.14812689528398,
              49.26423539325219
            ],
            [
              -123.14814539417256,
              49.26375735519022
            ]
          ]
        ],
        "type": "MultiLineString"
      },
      "properties": {}
    },
    "geo_point_2d": {
      "lon": -123.11828769589711,
      "lat": 49.26301034265017
    }
  }
]
